Metadata-Version: 2.1
Name: perIOdico
Version: 0.1.2
Summary: Download the first page of a newspaper given a date
Home-page: https://github.com/jtl125/perIOdico
Author: Arzdou
Author-email: arzdou@gmail.com
License: UNKNOWN
Project-URL: Bug Tracker, https://github.com/jtl125/perIOdico/issues
Platform: UNKNOWN
Classifier: Programming Language :: Python :: 3
Classifier: License :: OSI Approved :: MIT License
Classifier: Operating System :: OS Independent
Requires-Python: >=3.8
